{
  "host": "Host name here",
  "totalSteps": 4,
  "steps": {
    "1": {
      "form": "formA",
      "header": "Do you own or rent?",
      "buttonText": "Next",
      "formType": "radio",
      "inputs": [
        {
          "type": "radio",
          "id": "own",
          "label": "I own my property",
          "name": "own",
          "value": "I own my property"
        },
        {
          "type": "radio",
          "id": "rent",
          "name": "rent",
          "label": "I am renting",
          "value": "I am renting"
        }
      ]
    },
    "2": {
      "form": "formA",
      "header": "Click new to register with TTX",
      "subHeader": "We will automatically submit your info",
      "buttonText": "Next",
      "formType": "input",
      "inputs": [
        {
          "type": "number",
          "label": "Tax Id",
          "placeholder": "enter your personal tax id",
          "name": "taxId"
        },
        {
          "type": "number",
          "label": "Social Security Number",
          "placeholder": "Enter your SSN",
          "name": "ssn"
        }
      ]
    },
    "3": {
      "form": "formA",
      "header": "Click next to apply with OSTR",
      "subHeader": "We will automatically submit your info.",
      "buttonText": "Next",
      "formType": "input",
      "inputs": [
        {
          "type": "number",
          "label": "How many occupants will you be renting to each night?",
          "placeholder": "enter max number of occupants",
          "name": "numberOccupants"
        },
        {
          "type": "number",
          "label": "How much tax will you be charging per occupant?",
          "placeholder": "Enter percentage (%)",
          "name": "taxPercent"
        }
      ]
    },
    "4": {
      "form": "formA",
      "header": "Do you want to automatically renew?",
      "buttonText": "Finish",
      "formType": "radio",
      "inputs": [
        {
          "type": "radio",
          "id": "yes",
          "label": "Yes, that sounds great",
          "name": "yes",
          "value": "Yes, that sounds great"
        },
        {
          "type": "radio",
          "id": "no",
          "name": "no",
          "label": "Nope",
          "value": "Nope"
        }
      ]
    }
  }
}
